Workbook

Sheet Budget_Data_500
A1: Month | B1: Department | C1: Base_Revenue | D1: Best_Revenue | E1: Worst_Revenue | F1: Base_Cost | G1: Best_Cost | H1: Worst_Cost | I1: Base_Profit | J1: Best_Profit | K1: Worst_Profit
A2: Month 1 | B2: HR | C2: 491832 | D2: 565606 | E2: 418057 | F2: 273003 | G2: 245702 | H2: 300303 | I2: =C2-F2 | J2: =D2-G2 | K2: =E2-H2
A3: Month 1 | B3: IT | C3: 603045 | D3: 693501 | E3: 512588 | F3: 311636 | G3: 280472 | H3: 342799 | I3: =C3-F3 | J3: =D3-G3 | K3: =E3-H3
A4: Month 1 | B4: Sales | C4: 548901 | D4: 631236 | E4: 466565 | F4: 202337 | G4: 182103 | H4: 222570 | I4: =C4-F4 | J4: =D4-G4 | K4: =E4-H4
A5: Month 1 | B5: Marketing | C5: 470842 | D5: 541468 | E5: 400215 | F5: 273542 | G5: 246187 | H5: 300896 | I5: =C5-F5 | J5: =D5-G5 | K5: =E5-H5
A6: Month 1 | B6: Finance | C6: 463716 | D6: 533273 | E6: 394158 | F6: 329961 | G6: 296964 | H6: 362957 | I6: =C6-F6 | J6: =D6-G6 | K6: =E6-H6
A7: Month 2 | B7: HR | C7: 572238 | D7: 658073 | E7: 486402 | F7: 254142 | G7: 228727 | H7: 279556 | I7: =C7-F7 | J7: =D7-G7 | K7: =E7-H7
A8: Month 2 | B8: IT | C8: 623461 | D8: 716980 | E8: 529941 | F8: 284342 | G8: 255907 | H8: 312776 | I8: =C8-F8 | J8: =D8-G8 | K8: =E8-H8
A9: Month 2 | B9: Sales | C9: 408809 | D9: 470130 | E9: 347487 | F9: 306228 | G9: 275605 | H9: 336850 | I9: =C9-F9 | J9: =D9-G9 | K9: =E9-H9
A10: Month 2 | B10: Marketing | C10: 561106 | D10: 645271 | E10: 476940 | F10: 225905 | G10: 203314 | H10: 248495 | I10: =C10-F10 | J10: =D10-G10 | K10: =E10-H10
A11: Month 2 | B11: Finance | C11: 400183 | D11: 460210 | E11: 340155 | F11: 286948 | G11: 258253 | H11: 315642 | I11: =C11-F11 | J11: =D11-G11 | K11: =E11-H11
A12: Month 3 | B12: HR | C12: 581422 | D12: 668635 | E12: 494208 | F12: 309085 | G12: 278176 | H12: 339993 | I12: =C12-F12 | J12: =D12-G12 | K12: =E12-H12
A13: Month 3 | B13: IT | C13: 437693 | D13: 503346 | E13: 372039 | F13: 292122 | G13: 262909 | H13: 321334 | I13: =C13-F13 | J13: =D13-G13 | K13: =E13-H13
... A501: Month 100 | B501: Finance | C501: 455311 | D501: 523607 | E501: 387014 | F501: 206406 | G501: 185765 | H501: 227046 | I501: =C501-F501 | J501: =D501-G501 | K501: =E501-H501

Sheet Summary
A1: Department | B1: Base Profit | C1: Best Profit | D1: Worst Profit
A2: HR | B2: =SUMIF(Budget_Data_500!B:B, A2, Budget_Data_500!I:I) | C2: =SUMIF(Budget_Data_500!B:B, A2, Budget_Data_500!J:J) | D2: =SUMIF(Budget_Data_500!B:B, A2, Budget_Data_500!K:K)
A3: IT | B3: =SUMIF(Budget_Data_500!B:B, A3, Budget_Data_500!I:I) | C3: =SUMIF(Budget_Data_500!B:B, A3, Budget_Data_500!J:J) | D3: =SUMIF(Budget_Data_500!B:B, A3, Budget_Data_500!K:K)
A4: Sales | B4: =SUMIF(Budget_Data_500!B:B, A4, Budget_Data_500!I:I) | C4: =SUMIF(Budget_Data_500!B:B, A4, Budget_Data_500!J:J) | D4: =SUMIF(Budget_Data_500!B:B, A4, Budget_Data_500!K:K)
A5: Marketing | B5: =SUMIF(Budget_Data_500!B:B, A5, Budget_Data_500!I:I) | C5: =SUMIF(Budget_Data_500!B:B, A5, Budget_Data_500!J:J) | D5: =SUMIF(Budget_Data_500!B:B, A5, Budget_Data_500!K:K)
A6: Finance | B6: =SUMIF(Budget_Data_500!B:B, A6, Budget_Data_500!I:I) | C6: =SUMIF(Budget_Data_500!B:B, A6, Budget_Data_500!J:J) | D6: =SUMIF(Budget_Data_500!B:B, A6, Budget_Data_500!K:K)

Sheet Scenario_Summary
A1: Scenario | B1: Revenue | C1: Total Expenses | D1: Profit
A2: Best Case | B2: 120000 | C2: 60000 | D2: 60000
A3: Expected Case | B3: 100000 | C3: 65000 | D3: 35000
A4: Worst Case | B4: 85000 | C4: 70000 | D4: 15000
